sinapsis_doctr/__init__.py
sinapsis_doctr/helpers/__init__.py
sinapsis_doctr/helpers/tags.py
sinapsis_doctr/templates/__init__.py
sinapsis_doctr/templates/doc_tr_ocr_prediction.py
sinapsis_doctr-0.1.7.dist-info/licenses/LICENSE
sinapsis_doctr-0.1.7.dist-info/METADATA
sinapsis_doctr-0.1.7.dist-info/WHEEL
sinapsis_doctr-0.1.7.dist-info/top_level.txt
sinapsis_doctr-0.1.7.dist-info/RECORD
